pytest_docgen/__init__.py
pytest_docgen/pytest_docgen.py
pytest_docgen/sphinxext/__init__.py
pytest_docgen/sphinxext/collapsible_block.py
pytest_docgen/sphinxext/_static/css/collapsible_block.css
pytest_docgen/sphinxext/_static/js/collapsible_block.js
pytest_docgen/sphinxext/_templates/collapsible_block_epilogue.html
pytest_docgen/sphinxext/_templates/collapsible_block_prologue.html
pytest_docgen-1.3.0.dist-info/LICENSE
pytest_docgen-1.3.0.dist-info/METADATA
pytest_docgen-1.3.0.dist-info/WHEEL
pytest_docgen-1.3.0.dist-info/entry_points.txt
pytest_docgen-1.3.0.dist-info/top_level.txt
pytest_docgen-1.3.0.dist-info/RECORD
