Metadata-Version: 2.1
Name: pytest-docgen
Version: 1.3.0
Summary: An RST Documentation Generator for pytest-based test suites
Home-page: https://github.com/astraw38/pytest-docgen
Author: Ashley Straw
Author-email: as.fireflash38@gmail.com
Maintainer: Ashley Straw
Maintainer-email: as.fireflash38@gmail.com
License: UNKNOWN
Download-URL: https://github.com/astraw38/pytest-docgen/tarball/v1.3.0/
Keywords: pytest,sphinx,rst,testing
Platform: UNKNOWN
Classifier: Framework :: Pytest
Requires-Dist: rstcloth
Requires-Dist: tabulate
